octodns_azion/__init__.py
octodns_azion-1.1.0.dist-info/licenses/LICENSE
octodns_azion-1.1.0.dist-info/METADATA
octodns_azion-1.1.0.dist-info/WHEEL
octodns_azion-1.1.0.dist-info/top_level.txt
octodns_azion-1.1.0.dist-info/RECORD
