Metadata-Version: 2.4
Name: octodns-azion
Version: 1.1.0
Summary:  Azion DNS provider for octoDNS
Home-page: https://github.com/aziontech/octodns-azion
Author: Marcus Grando
Author-email: marcus.grando@azion.com
License: MIT
Requires-Python: >=3.9
License-File: LICENSE
Requires-Dist: octodns>=1.12.0
Requires-Dist: requests>=2.32.5
Provides-Extra: dev
Requires-Dist: pytest<9.0.0,>=8.0.0; extra == "dev"
Requires-Dist: pytest-cov>=6.0.0; extra == "dev"
Requires-Dist: pytest-network; extra == "dev"
Requires-Dist: black<26.0.0,>=24.3.0; extra == "dev"
Requires-Dist: build>=1.0.0; extra == "dev"
Requires-Dist: isort>=5.13.0; extra == "dev"
Requires-Dist: pyflakes>=3.2.0; extra == "dev"
Requires-Dist: readme_renderer[md]>=44.0; extra == "dev"
Requires-Dist: twine>=6.0.0; extra == "dev"
Provides-Extra: test
Requires-Dist: pytest<9.0.0,>=8.0.0; extra == "test"
Requires-Dist: pytest-cov>=6.0.0; extra == "test"
Requires-Dist: pytest-network; extra == "test"
Dynamic: author
Dynamic: author-email
Dynamic: description
Dynamic: description-content-type
Dynamic: home-page
Dynamic: license
Dynamic: license-file
Dynamic: provides-extra
Dynamic: requires-dist
Dynamic: requires-python
Dynamic: summary
